kwhelp/__init__.py
kwhelp/checks/__init__.py
kwhelp/decorator/__init__.py
kwhelp/exceptions/__init__.py
kwhelp/helper/__init__.py
kwhelp/helper/base.py
kwhelp/rules/__init__.py
kwargshelper-2.7.1.dist-info/LICENSE
kwargshelper-2.7.1.dist-info/METADATA
kwargshelper-2.7.1.dist-info/WHEEL
kwargshelper-2.7.1.dist-info/top_level.txt
kwargshelper-2.7.1.dist-info/RECORD
