Metadata-Version: 2.1
Name: kwargshelper
Version: 2.7.1
Summary: Manages testing for valid kwargs key, values pairs and assigns class attributes for pairs.
Home-page: https://github.com/Amourspirit/python-kwargshelper
Author: :Barry-Thomas-Paul: Moss
Author-email: bigbytetech@gmail.com
License: MIT
Keywords: python,kwargs,args,parse,helper
Platform: UNKNOWN
Classifier: License :: OSI Approved :: MIT License
Classifier: Programming Language :: Python :: 3
Classifier: Programming Language :: Python :: 3.6
Classifier: Programming Language :: Python :: 3.7
Classifier: Programming Language :: Python :: 3.8
Classifier: Programming Language :: Python :: 3.9
Requires-Python: >=3.6.0
License-File: LICENSE
